Metadata-Version: 2.1
Name: mygb-distributions
Version: 0.1
Summary: Gaussian and Binomial distributions
Author: Claudine Hernandez
Author-email: ch@email.com
